[
  {
    "anonymous_family": "Model AB",
    "public_id": "V001",
    "sanitized_test_summary_if_allowed": {
      "accuracy": 0.5233,
      "weighted_score": 0.9914
    },
    "sanitized_validation_summary": {
      "accuracy": 0.5467,
      "weighted_score": 1.2892
    },
    "status": "worked",
    "test": {
      "accuracy": 0.5233333333333333,
      "auc": 0.5252502780867631,
      "balanced_accuracy": 0.517797552836485,
      "calibration_error": 0.00456292122602453,
      "cumulative_return": 47.7204290983385,
      "direction_accuracy": 0.5233333333333333,
      "f1": 0.5971830985915493,
      "loss": 0.693802393236928,
      "max_drawdown": -14.385553599034832,
      "mcc": 0.03773333045092626,
      "precision": 0.53,
      "precision_up": 0.53,
      "recall": 0.6838709677419355,
      "recall_up": 0.6838709677419355,
      "sharpe": 4.681071493946079,
      "trade_count": 300.0,
      "trading_proxy_score": 4.681071493946079,
      "weighted_score": 0.9914404827279413
    },
    "train": {
      "accuracy": 0.56,
      "auc": 0.5691498741563668,
      "balanced_accuracy": 0.5591465076387887,
      "calibration_error": 0.025253661155700713,
      "cumulative_return": 13.493578308165022,
      "direction_accuracy": 0.56,
      "f1": 0.578544061302682,
      "loss": 0.6882199280077631,
      "max_drawdown": -31.303033129663568,
      "mcc": 0.11829301527757739,
      "precision": 0.578544061302682,
      "precision_up": 0.578544061302682,
      "recall": 0.578544061302682,
      "recall_up": 0.578544061302682,
      "sharpe": 0.7425865828851291,
      "trade_count": 500.0,
      "trading_proxy_score": 0.7425865828851291,
      "weighted_score": 0.634258658288513
    },
    "validation": {
      "accuracy": 0.5466666666666666,
      "auc": 0.5213333333333333,
      "balanced_accuracy": 0.5466666666666666,
      "calibration_error": 0.02614922424157462,
      "cumulative_return": 70.69501755812513,
      "direction_accuracy": 0.5466666666666666,
      "f1": 0.6344086021505376,
      "loss": 0.6960383196877734,
      "max_drawdown": -7.61420844946575,
      "mcc": 0.10639084227042907,
      "precision": 0.5315315315315315,
      "precision_up": 0.5315315315315315,
      "recall": 0.7866666666666666,
      "recall_up": 0.7866666666666666,
      "sharpe": 7.424922953302418,
      "trade_count": 300.0,
      "trading_proxy_score": 7.424922953302418,
      "weighted_score": 1.2891589619969084
    }
  }
]