[
  {
    "anonymous_family": "Model Z",
    "public_id": "V001",
    "sanitized_test_summary_if_allowed": {
      "accuracy": 0.7467,
      "weighted_score": 0.4486
    },
    "sanitized_validation_summary": {
      "accuracy": 0.77,
      "weighted_score": 0.2889
    },
    "status": "worked",
    "test": {
      "accuracy": 0.7466666666666667,
      "auc": 0.8489458813301456,
      "balanced_accuracy": 0.7181047598348185,
      "calibration_error": 0.016368004207799214,
      "cumulative_return": -54.36721240612316,
      "direction_accuracy": 0.7466666666666667,
      "f1": 0.5957446808510639,
      "loss": 0.39235323112858694,
      "max_drawdown": -55.20424305802936,
      "mcc": 0.4164075263025044,
      "precision": 0.5490196078431373,
      "precision_up": 0.5490196078431373,
      "recall": 0.6511627906976745,
      "recall_up": 0.6511627906976745,
      "sharpe": -2.980664550715253,
      "trade_count": 300.0,
      "trading_proxy_score": -2.980664550715253,
      "weighted_score": 0.4486002115951414
    },
    "train": {
      "accuracy": 0.936,
      "auc": 0.9918937271878449,
      "balanced_accuracy": 0.9387997623291741,
      "calibration_error": 0.015744753155102043,
      "cumulative_return": -109.69118834467521,
      "direction_accuracy": 0.936,
      "f1": 0.8814814814814814,
      "loss": 0.24226792110176193,
      "max_drawdown": -110.45378017692636,
      "mcc": 0.8414168560488635,
      "precision": 0.8263888888888888,
      "precision_up": 0.8263888888888888,
      "recall": 0.9444444444444444,
      "recall_up": 0.9444444444444444,
      "sharpe": -3.422560292427455,
      "trade_count": 500.0,
      "trading_proxy_score": -3.422560292427455,
      "weighted_score": 0.5937439707572545
    },
    "validation": {
      "accuracy": 0.77,
      "auc": 0.8471528471528471,
      "balanced_accuracy": 0.7635785267364215,
      "calibration_error": 0.019644965752079024,
      "cumulative_return": -84.67594687484747,
      "direction_accuracy": 0.77,
      "f1": 0.6634146341463414,
      "loss": 0.40235394442290334,
      "max_drawdown": -86.95032110920552,
      "mcc": 0.4992579202721542,
      "precision": 0.5964912280701754,
      "precision_up": 0.5964912280701754,
      "recall": 0.7472527472527473,
      "recall_up": 0.7472527472527473,
      "sharpe": -4.811239381538947,
      "trade_count": 300.0,
      "trading_proxy_score": -4.811239381538947,
      "weighted_score": 0.2888760618461053
    }
  },
  {
    "anonymous_family": "Model AF",
    "public_id": "V002",
    "sanitized_test_summary_if_allowed": {
      "accuracy": 0.7133,
      "weighted_score": 0.4563
    },
    "sanitized_validation_summary": {
      "accuracy": 0.7133,
      "weighted_score": 0.4045
    },
    "status": "worked",
    "test": {
      "accuracy": 0.7133333333333334,
      "auc": 0.7929254509889154,
      "balanced_accuracy": 0.6356226907194088,
      "calibration_error": 0.0954260755330324,
      "cumulative_return": -47.08985824212818,
      "direction_accuracy": 0.7133333333333334,
      "f1": 0.475609756097561,
      "loss": 0.522503928932349,
      "max_drawdown": -49.219256843992774,
      "mcc": 0.27963702673483815,
      "precision": 0.5,
      "precision_up": 0.5,
      "recall": 0.45348837209302323,
      "recall_up": 0.45348837209302323,
      "sharpe": -2.57039262394052,
      "trade_count": 300.0,
      "trading_proxy_score": -2.57039262394052,
      "weighted_score": 0.45629407093928137
    },
    "train": {
      "accuracy": 0.778,
      "auc": 0.8574611662846957,
      "balanced_accuracy": 0.648989898989899,
      "calibration_error": 0.0755071848034859,
      "cumulative_return": -86.35407578794192,
      "direction_accuracy": 0.778,
      "f1": 0.4688995215311005,
      "loss": 0.4583619513170425,
      "max_drawdown": -88.91356343072493,
      "mcc": 0.34769690220318455,
      "precision": 0.5903614457831325,
      "precision_up": 0.5903614457831325,
      "recall": 0.3888888888888889,
      "recall_up": 0.3888888888888889,
      "sharpe": -2.670900036673624,
      "trade_count": 500.0,
      "trading_proxy_score": -2.670900036673624,
      "weighted_score": 0.5109099963326376
    },
    "validation": {
      "accuracy": 0.7133333333333334,
      "auc": 0.7699142962300857,
      "balanced_accuracy": 0.6360481623639518,
      "calibration_error": 0.08257107391953467,
      "cumulative_return": -55.756004865225734,
      "direction_accuracy": 0.7133333333333334,
      "f1": 0.4819277108433735,
      "loss": 0.5481763604543282,
      "max_drawdown": -55.868491548768645,
      "mcc": 0.2888648004111216,
      "precision": 0.5333333333333333,
      "precision_up": 0.5333333333333333,
      "recall": 0.43956043956043955,
      "recall_up": 0.43956043956043955,
      "sharpe": -3.088690696290103,
      "trade_count": 300.0,
      "trading_proxy_score": -3.088690696290103,
      "weighted_score": 0.40446426370432303
    }
  },
  {
    "anonymous_family": "Model G",
    "public_id": "V003",
    "sanitized_test_summary_if_allowed": {
      "accuracy": 0.7333,
      "weighted_score": 0.4408
    },
    "sanitized_validation_summary": {
      "accuracy": 0.74,
      "weighted_score": 0.3902
    },
    "status": "worked",
    "test": {
      "accuracy": 0.7333333333333333,
      "auc": 0.8030319495761791,
      "balanced_accuracy": 0.6739839165398827,
      "calibration_error": 0.12336336719493068,
      "cumulative_return": -53.39565745404141,
      "direction_accuracy": 0.7333333333333333,
      "f1": 0.5348837209302325,
      "loss": 0.5422150478489359,
      "max_drawdown": -55.369053803229846,
      "mcc": 0.34796783307976525,
      "precision": 0.5348837209302325,
      "precision_up": 0.5348837209302325,
      "recall": 0.5348837209302325,
      "recall_up": 0.5348837209302325,
      "sharpe": -2.925573232162131,
      "trade_count": 300.0,
      "trading_proxy_score": -2.925573232162131,
      "weighted_score": 0.4407760101171202
    },
    "train": {
      "accuracy": 0.832,
      "auc": 0.9213776419658772,
      "balanced_accuracy": 0.7692895339954164,
      "calibration_error": 0.09829008603096007,
      "cumulative_return": -91.02944997129484,
      "direction_accuracy": 0.832,
      "f1": 0.6585365853658537,
      "loss": 0.39937273295220715,
      "max_drawdown": -95.02983119130872,
      "mcc": 0.5475050417457386,
      "precision": 0.675,
      "precision_up": 0.675,
      "recall": 0.6428571428571429,
      "recall_up": 0.6428571428571429,
      "sharpe": -2.819950203737149,
      "trade_count": 500.0,
      "trading_proxy_score": -2.819950203737149,
      "weighted_score": 0.5500049796262851
    },
    "validation": {
      "accuracy": 0.74,
      "auc": 0.8028287501971713,
      "balanced_accuracy": 0.7048214942951785,
      "calibration_error": 0.09686596178760132,
      "cumulative_return": -62.82089201875845,
      "direction_accuracy": 0.74,
      "f1": 0.5894736842105263,
      "loss": 0.523582026638307,
      "max_drawdown": -64.60676504072933,
      "mcc": 0.400482680538498,
      "precision": 0.5656565656565656,
      "precision_up": 0.5656565656565656,
      "recall": 0.6153846153846154,
      "recall_up": 0.6153846153846154,
      "sharpe": -3.4979492814771844,
      "trade_count": 300.0,
      "trading_proxy_score": -3.4979492814771844,
      "weighted_score": 0.39020507185228154
    }
  },
  {
    "anonymous_family": "Ensemble V004",
    "public_id": "V004",
    "sanitized_test_summary_if_allowed": {
      "accuracy": 0.7433,
      "weighted_score": 0.4859
    },
    "sanitized_validation_summary": {
      "accuracy": 0.7533,
      "weighted_score": 0.3185
    },
    "status": "worked",
    "test": {
      "accuracy": 0.7433333333333333,
      "auc": 0.7618724190393392,
      "balanced_accuracy": 0.6809932623342752,
      "calibration_error": 0.008888927888888898,
      "cumulative_return": -47.151840629573755,
      "direction_accuracy": 0.7433333333333333,
      "f1": 0.5443786982248521,
      "loss": 2.4468762004343168,
      "max_drawdown": -49.125236978762175,
      "mcc": 0.36591448604981236,
      "precision": 0.5542168674698795,
      "precision_up": 0.5542168674698795,
      "recall": 0.5348837209302325,
      "recall_up": 0.5348837209302325,
      "sharpe": -2.5738648058765605,
      "trade_count": 300.0,
      "trading_proxy_score": -2.5738648058765605,
      "weighted_score": 0.4859468527456772
    },
    "train": {
      "accuracy": 0.854,
      "auc": 0.9163165266106442,
      "balanced_accuracy": 0.7918894830659536,
      "calibration_error": 0.020666613066666673,
      "cumulative_return": -99.96435202473322,
      "direction_accuracy": 0.854,
      "f1": 0.6970954356846473,
      "loss": 0.7521874716222565,
      "max_drawdown": -100.98778485236306,
      "mcc": 0.6022686145687886,
      "precision": 0.7304347826086957,
      "precision_up": 0.7304347826086957,
      "recall": 0.6666666666666666,
      "recall_up": 0.6666666666666666,
      "sharpe": -3.1068512434634545,
      "trade_count": 500.0,
      "trading_proxy_score": -3.1068512434634545,
      "weighted_score": 0.5433148756536545
    },
    "validation": {
      "accuracy": 0.7533333333333333,
      "auc": 0.7868447342131553,
      "balanced_accuracy": 0.7205951942794048,
      "calibration_error": 0.016666703666666616,
      "cumulative_return": -77.1286620783836,
      "direction_accuracy": 0.7533333333333333,
      "f1": 0.6105263157894737,
      "loss": 1.9934148778288105,
      "max_drawdown": -78.91453510035451,
      "mcc": 0.4313246274417324,
      "precision": 0.5858585858585859,
      "precision_up": 0.5858585858585859,
      "recall": 0.6373626373626373,
      "recall_up": 0.6373626373626373,
      "sharpe": -4.348522679928024,
      "trade_count": 300.0,
      "trading_proxy_score": -4.348522679928024,
      "weighted_score": 0.3184810653405309
    }
  },
  {
    "anonymous_family": "Ensemble V005",
    "public_id": "V005",
    "sanitized_test_summary_if_allowed": {
      "accuracy": 0.7533,
      "weighted_score": 0.4443
    },
    "sanitized_validation_summary": {
      "accuracy": 0.7467,
      "weighted_score": 0.288
    },
    "status": "worked",
    "test": {
      "accuracy": 0.7533333333333333,
      "auc": 0.8420995435774832,
      "balanced_accuracy": 0.7019126276896327,
      "calibration_error": 0.0783858156452541,
      "cumulative_return": -56.29966657382948,
      "direction_accuracy": 0.7533333333333333,
      "f1": 0.5747126436781609,
      "loss": 0.46977528003094504,
      "max_drawdown": -58.27306292301789,
      "mcc": 0.4010886035018499,
      "precision": 0.5681818181818182,
      "precision_up": 0.5681818181818182,
      "recall": 0.5813953488372093,
      "recall_up": 0.5813953488372093,
      "sharpe": -3.090554943979417,
      "trade_count": 300.0,
      "trading_proxy_score": -3.090554943979417,
      "weighted_score": 0.4442778389353916
    },
    "train": {
      "accuracy": 0.878,
      "auc": 0.9538239538239538,
      "balanced_accuracy": 0.823720397249809,
      "calibration_error": 0.06318067466318267,
      "cumulative_return": -103.33839379383221,
      "direction_accuracy": 0.878,
      "f1": 0.7468879668049793,
      "loss": 0.35658031991757244,
      "max_drawdown": -104.36182662146206,
      "mcc": 0.6679467622862137,
      "precision": 0.782608695652174,
      "precision_up": 0.782608695652174,
      "recall": 0.7142857142857143,
      "recall_up": 0.7142857142857143,
      "sharpe": -3.2159457451000684,
      "trade_count": 500.0,
      "trading_proxy_score": -3.2159457451000684,
      "weighted_score": 0.5564054254899932
    },
    "validation": {
      "accuracy": 0.7466666666666667,
      "auc": 0.8341132551658867,
      "balanced_accuracy": 0.7127083442872917,
      "calibration_error": 0.0663606671530717,
      "cumulative_return": -81.03224498614924,
      "direction_accuracy": 0.7466666666666667,
      "f1": 0.6000000000000001,
      "loss": 0.47712141507347183,
      "max_drawdown": -82.81811800812012,
      "mcc": 0.4159036539901152,
      "precision": 0.5757575757575758,
      "precision_up": 0.5757575757575758,
      "recall": 0.6263736263736264,
      "recall_up": 0.6263736263736264,
      "sharpe": -4.5865013734135776,
      "trade_count": 300.0,
      "trading_proxy_score": -4.5865013734135776,
      "weighted_score": 0.2880165293253089
    }
  },
  {
    "anonymous_family": "Ensemble V006",
    "public_id": "V006",
    "sanitized_test_summary_if_allowed": {
      "accuracy": 0.7267,
      "weighted_score": 0.7241
    },
    "sanitized_validation_summary": {
      "accuracy": 0.7267,
      "weighted_score": 0.7059
    },
    "status": "worked",
    "test": {
      "accuracy": 0.7266666666666667,
      "auc": 0.8465007607041948,
      "balanced_accuracy": 0.5545533579656596,
      "calibration_error": 0.01995473079797394,
      "cumulative_return": -0.4801792075585105,
      "direction_accuracy": 0.7266666666666667,
      "f1": 0.24074074074074076,
      "loss": 0.4836264089544405,
      "max_drawdown": -9.363233341800852,
      "mcc": 0.18926654653173972,
      "precision": 0.5909090909090909,
      "precision_up": 0.5909090909090909,
      "recall": 0.1511627906976744,
      "recall_up": 0.1511627906976744,
      "sharpe": -0.02587356138255554,
      "trade_count": 300.0,
      "trading_proxy_score": -0.02587356138255554,
      "weighted_score": 0.7240793105284111
    },
    "train": {
      "accuracy": 0.814,
      "auc": 0.979967744673627,
      "balanced_accuracy": 0.6309523809523809,
      "calibration_error": 0.03305598013540201,
      "cumulative_return": -37.86351484169404,
      "direction_accuracy": 0.814,
      "f1": 0.41509433962264153,
      "loss": 0.3937249963269468,
      "max_drawdown": -46.94095233050997,
      "mcc": 0.4579826842625467,
      "precision": 1.0,
      "precision_up": 1.0,
      "recall": 0.2619047619047619,
      "recall_up": 0.2619047619047619,
      "sharpe": -1.1579408046421338,
      "trade_count": 500.0,
      "trading_proxy_score": -1.1579408046421338,
      "weighted_score": 0.6982059195357866
    },
    "validation": {
      "accuracy": 0.7266666666666667,
      "auc": 0.8421052631578947,
      "balanced_accuracy": 0.5556548714443451,
      "calibration_error": 0.008811467224007496,
      "cumulative_return": -3.8159670669124233,
      "direction_accuracy": 0.7266666666666667,
      "f1": 0.21153846153846154,
      "loss": 0.49358891269357114,
      "max_drawdown": -24.91209743271216,
      "mcc": 0.25131267582032213,
      "precision": 0.8461538461538461,
      "precision_up": 0.8461538461538461,
      "recall": 0.12087912087912088,
      "recall_up": 0.12087912087912088,
      "sharpe": -0.20751796379169918,
      "trade_count": 300.0,
      "trading_proxy_score": -0.20751796379169918,
      "weighted_score": 0.7059148702874968
    }
  }
]